rchat/cli.py
rchat-0.0.2.dist-info/entry_points.txt
rchat-0.0.2.dist-info/LICENSE
rchat-0.0.2.dist-info/WHEEL
rchat-0.0.2.dist-info/METADATA
rchat-0.0.2.dist-info/RECORD
