Metadata-Version: 2.1
Name: rchat
Version: 0.0.2
Summary: A simple RocketChat command line client
Home-page: https://github.com/jvrsantacruz/rchat
License: GPL-3.0-only
Keywords: rocketchat,command-line,python
Author: Javier Santacruz
Author-email: javier.santacruz.lc@gmail.com
Requires-Python: >=3.7,<4.0
Classifier: Intended Audience :: Developers
Classifier: Intended Audience :: System Administrators
Classifier: License :: OSI Approved :: GNU General Public License v3 (GPLv3)
Classifier: Programming Language :: Python :: 3
Classifier: Programming Language :: Python :: 3.7
Classifier: Programming Language :: Python :: 3.8
Classifier: Topic :: Communications :: Chat
Requires-Dist: cached-property (>=1.5.1,<2.0.0)
Requires-Dist: click (>=7.1.2,<8.0.0)
Requires-Dist: confight (>=1.3.1,<2.0.0)
Requires-Dist: rocketchat-API (>=1.3.1,<2.0.0)
Project-URL: Documentation, https://github.com/jvrsantacruz/rchat
Project-URL: Repository, https://github.com/jvrsantacruz/rchat
